calculate/__init__.py
calculate/calc.py
calculate/temp_dir.py
calculate/unit_tests.py
example_pkg_naturalett-14.9.data/scripts/calc.py
example_pkg_naturalett-14.9.dist-info/METADATA
example_pkg_naturalett-14.9.dist-info/WHEEL
example_pkg_naturalett-14.9.dist-info/top_level.txt
example_pkg_naturalett-14.9.dist-info/RECORD
